docs/source/conf.py
embodichain/VERSION
embodichain/__init__.py
embodichain/__pycache__/__init__.cpython-310.pyc
embodichain/agents/hierarchy/__init__.py
embodichain/agents/hierarchy/agent_base.py
embodichain/agents/hierarchy/code_agent.py
embodichain/agents/hierarchy/llm.py
embodichain/agents/hierarchy/task_agent.py
embodichain/agents/hierarchy/validation_agent.py
embodichain/agents/mllm/prompt/__init__.py
embodichain/agents/mllm/prompt/code_prompt.py
embodichain/agents/mllm/prompt/task_prompt.py
embodichain/agents/prompts/atom_actions.txt
embodichain/agents/prompts/basic_background.txt
embodichain/agents/prompts/code_example.txt
embodichain/agents/prompts/code_prompt.txt
embodichain/agents/rl/train.py
embodichain/agents/rl/__pycache__/train.cpython-310.pyc
embodichain/agents/rl/algo/__init__.py
embodichain/agents/rl/algo/base.py
embodichain/agents/rl/algo/ppo.py
embodichain/agents/rl/algo/__pycache__/__init__.cpython-310.pyc
embodichain/agents/rl/algo/__pycache__/base.cpython-310.pyc
embodichain/agents/rl/algo/__pycache__/ppo.cpython-310.pyc
embodichain/agents/rl/buffer/__init__.py
embodichain/agents/rl/buffer/rollout_buffer.py
embodichain/agents/rl/buffer/__pycache__/__init__.cpython-310.pyc
embodichain/agents/rl/buffer/__pycache__/rollout_buffer.cpython-310.pyc
embodichain/agents/rl/models/__init__.py
embodichain/agents/rl/models/actor_critic.py
embodichain/agents/rl/models/mlp.py
embodichain/agents/rl/models/policy.py
embodichain/agents/rl/models/__pycache__/__init__.cpython-310.pyc
embodichain/agents/rl/models/__pycache__/actor_critic.cpython-310.pyc
embodichain/agents/rl/models/__pycache__/mlp.cpython-310.pyc
embodichain/agents/rl/models/__pycache__/policy.cpython-310.pyc
embodichain/agents/rl/utils/__init__.py
embodichain/agents/rl/utils/config.py
embodichain/agents/rl/utils/helper.py
embodichain/agents/rl/utils/trainer.py
embodichain/agents/rl/utils/__pycache__/__init__.cpython-310.pyc
embodichain/agents/rl/utils/__pycache__/config.cpython-310.pyc
embodichain-0.1.0.dist-info/licenses/LICENSE
embodichain-0.1.0.dist-info/METADATA
embodichain-0.1.0.dist-info/WHEEL
embodichain-0.1.0.dist-info/top_level.txt
embodichain-0.1.0.dist-info/RECORD
