Metadata-Version: 2.4
Name: embodichain
Version: 0.1.0
Summary: An end-to-end, GPU-accelerated, and modular platform for building generalized Embodied Intelligence.
Home-page: https://github.com/DexForce/EmbodiChain
Author: EmbodiChain Developers
Requires-Python: >=3.10
License-File: LICENSE
Requires-Dist: dexsim_engine==0.3.9
Requires-Dist: setuptools>=78.1.1
Requires-Dist: gymnasium>=0.29.1
Requires-Dist: langchain
Requires-Dist: langchain-openai
Requires-Dist: toppra==0.6.3
Requires-Dist: pin
Requires-Dist: pin-pink
Requires-Dist: casadi
Requires-Dist: qpsolvers==4.8.1
Requires-Dist: py_opw_kinematics==0.1.6
Requires-Dist: pytorch_kinematics==0.7.6
Requires-Dist: polars==1.31.0
Requires-Dist: PyYAML>=6.0
Requires-Dist: accelerate>=1.10.0
Requires-Dist: wandb>=0.21.0
Requires-Dist: tensorboard>=2.20.0
Requires-Dist: transformers>=4.53.0
Requires-Dist: diffusers>=0.32.1
Requires-Dist: deepspeed>=0.16.2
Requires-Dist: ortools
Requires-Dist: prettytable
Requires-Dist: black==24.3.0
Requires-Dist: fvcore
Requires-Dist: h5py
Provides-Extra: lerobot
Requires-Dist: lerobot==0.4.2; extra == "lerobot"
Dynamic: home-page
Dynamic: license-file
